.travis.yml
README.rst
bootstrap.py
buildout.cfg
setup.cfg
setup.py
validation-files.yaml
validation-options.yaml
docs/HISTORY.rst
docs/LICENSE.rst
docs/api.rst
docs/conf.py
docs/conventions.rst
docs/env.rst
docs/index.rst
docs/release.rst
src/spinnerchief/__init__.py
src/spinnerchief/exceptions.py
src/spinnerchief/version.txt
src/spinnerchief.egg-info/PKG-INFO
src/spinnerchief.egg-info/SOURCES.txt
src/spinnerchief.egg-info/dependency_links.txt
src/spinnerchief.egg-info/not-zip-safe
src/spinnerchief.egg-info/requires.txt
src/spinnerchief.egg-info/top_level.txt
src/spinnerchief/tests/__init__.py
src/spinnerchief/tests/test_spinnerchief.py