Metadata-Version: 1.1
Name: spinnerchief
Version: 0.1
Summary: Python bindings for SpinnerChief API
Home-page: http://www.niteoweb.com
Author: NiteoWeb Ltd.
Author-email: info@niteoweb.com
License: BSD
Keywords: API spinner SpinnerChief
Platform: UNKNOWN
Classifier: Programming Language :: Python
Classifier: Topic :: Internet :: WWW/HTTP
